Metadata-Version: 2.4
Name: x_make_graphviz_x
Version: 12.0.0
Summary: Graphviz diagram builder.
Author-email: RRGM of the Primus Pilus Night Watch AI Corporation <eye4357@outlook.com>
License-Expression: MIT
